odoo/addons/purchase_substate/README.rst
odoo/addons/purchase_substate/__init__.py
odoo/addons/purchase_substate/__manifest__.py
odoo/addons/purchase_substate/data/purchase_substate_data.xml
odoo/addons/purchase_substate/data/purchase_substate_mail_template_data.xml
odoo/addons/purchase_substate/demo/purchase_substate_demo.xml
odoo/addons/purchase_substate/i18n/it.po
odoo/addons/purchase_substate/i18n/purchase_substate.pot
odoo/addons/purchase_substate/models/__init__.py
odoo/addons/purchase_substate/models/purchase_order.py
odoo/addons/purchase_substate/readme/CONTRIBUTORS.md
odoo/addons/purchase_substate/readme/DESCRIPTION.md
odoo/addons/purchase_substate/readme/USAGE.md
odoo/addons/purchase_substate/static/description/icon.png
odoo/addons/purchase_substate/static/description/index.html
odoo/addons/purchase_substate/tests/__init__.py
odoo/addons/purchase_substate/tests/test_purchase_substate.py
odoo/addons/purchase_substate/views/purchase_views.xml
odoo_addon_purchase_substate-18.0.1.0.0.4.dist-info/METADATA
odoo_addon_purchase_substate-18.0.1.0.0.4.dist-info/WHEEL
odoo_addon_purchase_substate-18.0.1.0.0.4.dist-info/top_level.txt
odoo_addon_purchase_substate-18.0.1.0.0.4.dist-info/RECORD
